{
        "abajo": "下に",
        "abierto": "開いている",
        "abierta": "開いている",
        "abrigo": "コート",
        "abril": "4月",
        "abrir": "開く",
        "absoluto": "絶対",
        "absoluta": "絶対",
        "abuelo": "祖父",
        "abuela": "祖母",
        "aburrido": "つまらない",
        "aburrida": "つまらない",
        "acabar": "終わり",
        "accidente": "事故",
        "acción": "アクション",
        "aceptar": "受け入れる",
        "acompañar": "付き添う",
        "aconsejar": "アドバイス",
        "acordarse": "思い出す",
        "acostarse": "寝る",
        "acostumbrado": "なれた",
        "acostumbrada": "なれた",
        "actividad": "活動",
        "actor": "俳優",
        "actriz": "女優",
        "actual": "現在",
        "acuerdo": "合意",
        "adelante": "進め",
        "además": "そのほか",
        "adiós": "ではまた",
        "admirable": "見事",
        "advertir": "警告",
        "aeropuerto": "空港",
        "aficionado": "アマチュア",
        "aficionada": "アマチュア",
        "afeitarse": "剃る",
        "afuera": "外",
        "agencia": "代理店",
        "agosto": "8月",
        "agradable": "快適",
        "agradecer": "感謝する",
        "agua": "水",
        "ahí": "そこ",
        "ahora": "今",
        "aire": "空気",
        "aire acondicionado": "エアコン",
        "ajedrez": "チェス",
        "alcanzar": "届く",
        "aldea": "村",
        "alegrar": "喜ぶ",
        "alegre": "陽気",
        "Alemania": "ドイツ",
        "aleman": "ドイツ語",
        "alfombra": "カーペット",
        "algo": "何か",
        "algodón": "綿",
        "alguien": "誰か",
        "alguno": "いくつか",
        "alguna": "いくつか",
        "allí": "そこ",
        "almacén": "倉庫",
        "almohada": "枕",
        "almorzar": "昼食をとる",
        "almuerzo": "昼食",
        "alquilar": "借りる",
        "alrededor": "周り",
        "alto": "高い",
        "alta": "高い",
        "altura": "高さ",
        "alumno": "生徒",
        "alumna": "生徒",
        "amable": "親切な",
        "amanecer": "夜明け",
        "amar": "愛する",
        "amarillo": "黄色",
        "amarilla": "黄色",
        "América": "アメリカ",
        "América Latina": "ラテンアメリカ",
        "amigo": "友達",
        "amiga": "友達",
        "amor": "愛",
        "ancho": "広い",
        "ancha": "広い",
        "anciano": "老人",
        "anciana": "老女",
        "andar": "歩く",
        "andén": "プラットフォーム",
        "anillo": "指輪",
        "animal": "動物",
        "ánimo": "気持ち",
        "aniversario": "記念日",
        "anoche": "昨夜",
        "anteayer": "一昨日",
        "anterior": "前",
        "antes": "前",
        "antiguo": "古い",
        "antigua": "古い",
        "antipático": "不愉快な",
        "antipática": "不愉快な",
        "año": "年",
        "apagar": "消す",
        "aparcar": "駐車する",
        "aparecer": "現れる",
        "apetito": "食欲",
        "aplicado": "熱心な",
        "aplicada": "熱心な",
        "aprender": "学ぶ",
        "aproximadamente": "約",
        "aquel": "あの",
        "aquella": "あの",
        "aquello": "それ",
        "aquí": "ここ",
        "árbol": "木",
        "arcoíris": "虹",
        "arena": "砂",
        "Argentina": "アルゼンチン",
        "argentino": "アルゼンチン人",
        "argentina": "アルゼンチン",
        "armario": "戸棚",
        "arrepentirse": "後悔する",
        "arriba": "上に",
        "arroz": "米",
        "arte": "芸術",
        "artículo": "記事",
        "ascensor": "エレベーター",
        "aseo": "トイレ",
        "así": "そのように",
        "Asia": "アジア",
        "asiático": "アジアの",
        "asiática": "アジアの",
        "asiento": "座席",
        "asistir": "出席する",
        "aspecto": "外観",
        "asunto": "件名",
        "atención": "注意",
        "atentamente": "敬具",
        "átomo": "原子",
        "atrás": "後ろ",
        "atreverse": "思い切って",
        "aula": "教室",
        "aun": "まだ",
        "aún": "まだ",
        "aunque": "しかし",
        "ausente": "不在",
        "autobús": "バス",
        "automático": "自動的な",
        "automática": "自動的な",
        "ave": "鳥（とり）",
        "avión": "飛行機",
        "ayer": "昨日",
        "ayuda": "助け",
        "ayudar": "助ける",
        "ayuntamiento": "市役所",
        "azul": "青い",
        "bailar": "踊る",
        "baile": "ダンス",
        "bajar": "下がる",
        "bajo": "低い",
        "baja": "低い",
        "baloncesto": "バスケットボール",
        "básquetbol": "バスケットボール",
        "balonmano": "ハンドボール",
        "banco": "銀行",
        "bandera": "旗",
        "bañar": "入浴させる",
        "baño": "バスルーム",
        "bar": "バー",
        "barato": "安い",
        "barata": "安い",
        "barba": "ひげ",
        "barco": "船",
        "barrio": "地区",
        "bádminton": "バドミントン",
        "básico": "基本的な",
        "básica": "基本的な",
        "bastar": "十分である",
        "basura": "ごみ",
        "bebé": "赤ちゃん",
        "beber": "飲む",
        "béisbol": "野球",
        "belleza": "美しさ",
        "bello": "美しい",
        "bella": "美しい",
        "beso": "キス",
        "biblioteca": "図書館",
        "bicho": "虫（むし）",
        "bicicleta": "自転車",
        "billete": "チケット",
        "bien": "よく",
        "bienvenido": "ようこそ",
        "bienvenida": "ようこそ",
        "bigote": "髭（口ひげ）",
        "blanco": "白い",
        "blanca": "白い",
        "boca": "口",
        "boda": "結婚式",
        "bolígrafo": "ボールペン",
        "bolos": "ボーリング",
        "bolsa": "袋、バッグ",
        "bolsillo": "ポケット",
        "bolso": "鞄",
        "bonito": "きれいな",
        "bonita": "きれいな",
        "bosque": "森",
        "botella": "ボトル",
        "boxeo": "ボクシング",
        "Brasil": "ブラジル",
        "brasileño": "ブラジル人",
        "brasileña": "ブラジル人",
        "brazo": "アーム",
        "brillante": "明るい",
        "bueno": "良い",
        "buena": "良い",
        "buscar": "探す",
        "cabello": "髪",
        "caber": "収まる",
        "cabeza": "頭",
        "cada": "毎",
        "caer": "落ちる",
        "café": "コーヒー",
        "caja": "箱",
        "cajón": "引き出し",
        "caliente": "暖かい",
        "callar": "黙る",
        "calle": "通り",
        "calor": "暑さ",
        "cama": "ベッド",
        "camarero": "ウェイター",
        "camarera": "ウェイトレス",
        "cambiar": "変える",
        "cambio": "変化",
        "caminar": "歩く",
        "camino": "道",
        "camión": "トラック",
        "camisa": "シャツ",
        "camiseta": "Tシャツ",
        "campana": "鐘、ベル",
        "campo": "野原",
        "Canadá": "カナダ",
        "canción": "歌",
        "cansado": "疲れた",
        "cansada": "疲れた",
        "cantar": "歌う",
        "cámara": "カメラ",
        "cántaro": "水差し",
        "capital": "首都",
        "cáracter": "性格",
        "carne": "肉",
        "caro": "高価な",
        "cara": "顔",
        "carretera": "道路",
        "carta": "手紙",
        "cartera": "財布",
        "casa": "家",
        "casado": "既婚の",
        "casada": "既婚の",
        "casarse": "結婚する",
        "casco": "ヘルメット",
        "casi": "ほぼ",
        "caso": "場合",
        "castellano": "スペイン語",
        "castellana": "スペイン語",
        "castillo": "城",
        "catedral": "大聖堂",
        "católico": "カトリック",
        "católica": "カトリック",
        "cebolla": "玉ねぎ",
        "ceja": "眉",
        "celebrar": "祝う",
        "cena": "夕食",
        "cenar": "夕食をとる",
        "centro": "中心",
        "cepillo": "ブラシ",
        "cerca": "近く",
        "cerdo": "豚肉",
        "cerebro": "脳",
        "cerrado": "閉じた",
        "cerrada": "閉じた",
        "cerrar": "閉じる",
        "cerveza": "ビール",
        "chalet": "別荘",
        "chalé": "別荘",
        "chaqueta": "ジャケット",
        "charlar": "おしゃべりをする",
        "chico": "少年",
        "chica": "少女",
        "Chile": "チリ",
        "chileno": "チリの",
        "chilena": "チリの",
        "China": "中国",
        "chino": "中国人",
        "china": "中国の陶磁器",
        "chiste": "冗談",
        "chocolate": "チョコレート",
        "ciclomotor": "原付",
        "cielo": "空",
        "ciento": "100",
        "cierto": "確かな",
        "cierta": "確かな",
        "cine": "映画",
        "cintura": "腰",
        "cinturón": "ベルト",
        "círculo": "円",
        "cita": "約束",
        "ciudad": "都市",
        "claro": "明らか",
        "clara": "明るい",
        "clase": "授業",
        "clima": "気候",
        "clínica": "クリニック",
        "coche": "車",
        "cocina": "台所",
        "cocinar": "料理する",
        "cocinero": "料理人",
        "cocinera": "料理人",
        "codo": "肘",
        "coger": "取る",
        "cola": "尾",
        "colegio": "学校",
        "colgar": "掛ける",
        "Colombia": "コロンビア",
        "colombiano": "コロンビア人",
        "colombiana": "コロンビア人",
        "color": "色",
        "comedor": "食堂",
        "comenzar": "始まる",
        "comer": "食べる",
        "comida": "食べ物",
        "como": "～のように",
        "cómo": "どのように",
        "cómodo": "快適な",
        "cómoda": "快適な",
        "compañero": "同僚",
        "compañera": "同僚",
        "compañia": "会社",
        "compra": "購入",
        "comprar": "買う",
        "comprender": "理解する",
        "común": "一般的な",
        "comunicación por chat": "チャット",
        "concierto": "コンサート",
        "condición": "状態",
        "conducir": "運転する",
        "conductor": "運転手",
        "conductora": "運転手",
        "conejo": "兎（うさぎ）",
        "coneja": "兎（うさぎ）",
        "conferencia": "会議",
        "contferencia": "会議",
        "conmigo": "私と一緒に",
        "conocer": "知る",
        "conocido": "知られた",
        "conocida": "知られた",
        "construcción": "建設",
        "construir": "建てる",
        "consultar": "参照する",
        "contar": "数える",
        "contento": "満足した",
        "contenta": "満足した",
        "contestar": "答える",
        "contigo": "あなたと一緒に",
        "continente": "大陸",
        "control remoto": "リモコン",
        "convertirse": "変わる",
        "copia": "コピー",
        "corazón": "心臓",
        "corbata": "ネクタイ",
        "coreano": "韓国人",
        "coreana": "韓国人",
        "correcto": "正しい",
        "correcta": "正しい",
        "correo": "郵便",
        "correo electrónico": "メール",
        "correr": "走る",
        "cortar": "切る",
        "corto": "短い",
        "corta": "短い",
        "cosa": "物",
        "costa": "海岸",
        "costar": "価値がある",
        "costumbre": "習慣",
        "creer": "信じる",
        "crema": "クリーム",
        "cristiano": "キリスト教の",
        "cristiana": "キリスト教の",
        "cuaderno": "ノート",
        "cuadrado": "四角",
        "cuadro": "絵",
        "cuál": "どの",
        "cualquiera": "どれでも",
        "cuando": "いつ",
        "cuándo": "いつ",
        "cuanto": "どれだけ",
        "cuanta": "いくつか",
        "cuánto": "どれだけ",
        "cuánta": "いくつか",
        "cuarto": "4番目、部屋",
        "cuarta": "4番目",
        "Cuba": "キューバ",
        "cubrir": "覆う",
        "cuello": "首",
        "cuenta": "アカウント",
        "cuento": "物語",
        "cuero": "革",
        "cuerpo": "体",
        "cuidado": "注意",
        "culpa": "過失",
        "cultura": "文化",
        "curling": "カーリング",
        "cumpleaños": "誕生日",
        "cumplir": "遂行する",
        "curso": "コース",
        "dado": "サイコロ",
        "daño": "損傷",
        "dar": "与える",
        "debajo de": "下に",
        "deber": "するべきである",
        "decir": "言う",
        "declarar": "宣言する",
        "dedicar": "捧げる",
        "dedo": "指",
        "dejar": "置く",
        "delante": "前に",
        "demasiado": "あまりにも",
        "demasiada": "あまりにも",
        "dentista": "歯医者",
        "dentro": "内部",
        "dependiente": "店員",
        "dependienta": "店員",
        "deporte": "スポーツ",
        "derecho": "右",
        "derecha": "右",
        "desayunar": "朝食を取る",
        "desayuno": "朝食",
        "descansar": "休憩する",
        "descanso": "休憩",
        "desear": "願う",
        "desde": "から",
        "despacio": "ゆっくり",
        "despedir": "別れる",
        "despejado": "晴れ",
        "despejada": "晴れ",
        "despertarse": "目を覚ます",
        "después": "後で",
        "destino": "目的地",
        "determinar": "決定する",
        "detrás": "後ろ",
        "devolver": "返す",
        "día": "日",
        "diamante": "ダイアモンド",
        "diario": "日刊の",
        "diaria": "日刊の",
        "diccionario": "辞書",
        "dicho": "言われた",
        "dicha": "幸せ",
        "diciembre": "12月",
        "diente": "歯",
        "diferente": "異なる",
        "difícil": "難しい",
        "dinero": "お金",
        "dios": "神",
        "dirección": "方向",
        "director": "監督",
        "directora": "監督",
        "disco": "ディスク",
        "distinto": "異なる",
        "distinta": "異なる",
        "diverso": "さまざまな",
        "diversa": "さまざまな",
        "divertido": "楽しい",
        "divertida": "楽しい",
        "doble": "2重の",
        "doctor": "医師",
        "doctora": "医師",
        "doler": "痛む",
        "dolor": "痛み",
        "domingo": "日曜日",
        "donde": "どこ",
        "Dónde": "どこ",
        "dormir": "眠る",
        "dormitorio": "寝室",
        "ducha": "シャワー",
        "duda": "疑問",
        "dudar": "疑う",
        "dulce": "甘い",
        "durante": "中に",
        "durar": "持続する",
        "echar": "投げる",
        "economia": "経済",
        "edad": "年齢",
        "edificio": "建物",
        "efectivo": "現金",
        "ejemplo": "例",
        "ejercicio": "エクササイズ",
        "él": "彼",
        "electricidad": "電気",
        "elegante": "エレガント",
        "elegir": "選ぶ",
        "ella": "彼女",
        "ellas": "彼女たち",
        "ellos": "彼ら",
        "e-mail": "電子メール",
        "embajada": "大使館",
        "empezar": "始める",
        "empleado": "従業員",
        "empleada": "従業員",
        "empresa": "企業",
        "empujar": "押す",
        "enamorado": "恋している",
        "enamorada": "恋している",
        "encantado": "喜んで",
        "encantada": "魅了された",
        "encantar": "魅了する",
        "encender": "点ける",
        "enchufe de salida": "コンセント",
        "encima": "上に",
        "encontrar": "見つける",
        "enero": "1月",
        "enfadarse": "怒る",
        "enfermedad": "病気",
        "enfermero": "看護師",
        "enfermera": "看護師",
        "enfermo": "病気",
        "enferma": "病気",
        "enfrente": "向かい側",
        "ensalada": "サラダ",
        "enseguida": "すぐに",
        "enseñar": "教える",
        "entender": "理解する",
        "entero": "全体の",
        "entera": "全体の",
        "entonces": "それから",
        "entrada": "入り口",
        "entrar": "入る",
        "entre": "間に",
        "enviar": "送る",
        "época": "時代",
        "equipaje": "荷物",
        "equipo": "チーム",
        "escalada": "登山",
        "escalera": "階段",
        "escáner": "スキャナー",
        "escondite": "隠れ場",
        "escribir": "書く",
        "escrito": "書かれた",
        "escrita": "書かれた",
        "escritor": "作家",
        "escritora": "作家",
        "escritorio": "デスク",
        "escuchar": "聞く",
        "escuela": "学校",
        "ese": "その",
        "esa": "その",
        "espalda": "背中",
        "Espana": "スペイン",
        "especial": "特別な",
        "espejo": "鏡",
        "esperar": "期待する",
        "esposo": "夫",
        "esposa": "妻",
        "esquiar": "スキーをする",
        "esquina": "角",
        "estación": "駅",
        "estadio": "スタジアム",
        "estado": "状態",
        "Estados Unidos": "アメリカ合衆国",
        "estanco": "喫煙所",
        "estar": "〜である",
        "este": "この",
        "esta": "この",
        "estómago": "胃",
        "estrecho": "狭い",
        "estrecha": "狭い",
        "estrella": "星",
        "estudiante": "学生",
        "estudiar": "勉強する",
        "estudio": "研究",
        "estupendo": "素晴らしい",
        "estupenda": "素晴らしい",
        "euro": "ユーロ",
        "Europa": "ヨーロッパ",
        "exacto": "正確な",
        "exacta": "正確な",
        "examen": "試験",
        "excelente": "優れた",
        "excursión": "遠足",
        "éxito": "成功",
        "explicar": "説明する",
        "exposición": "展示",
        "expreso": "特急",
        "expresa": "表現する",
        "extintor": "消火器",
        "extranjero": "外国の",
        "extranjera": "外国の",
        "extraño": "奇妙な",
        "extraña": "奇妙な",
        "extraordinario": "非凡な",
        "extraordinaria": "非凡な",
        "extremo": "極端",
        "extrema": "極端な",
        "fábrica": "工場",
        "fácil": "簡単な",
        "falda": "スカート",
        "falso": "偽の",
        "falsa": "偽の",
        "falta": "不足",
        "familia": "家族",
        "famoso": "有名な",
        "famosa": "有名な",
        "farmacia": "薬局",
        "favor": "好意",
        "favorito": "お気に入りの",
        "favorita": "お気に入りの",
        "febrero": "2月",
        "fecha": "日付",
        "feliz": "幸せな",
        "felices": "幸せな",
        "fiebre": "熱",
        "fiesta": "パーティー",
        "fin": "終わり",
        "final": "最後の",
        "firme": "しっかりした",
        "flor": "花",
        "fondo": "背景",
        "forma": "形",
        "formar": "形作る",
        "foto": "写真",
        "Francia": "フランス",
        "frase": "フレーズ",
        "frecuencia": "頻度",
        "frecuente": "頻繁な",
        "frente": "前面",
        "fresco": "新鮮な",
        "fresca": "新鮮な",
        "frio": "冷たい",
        "fria": "冷たい",
        "fruta": "フルーツ",
        "fuego": "火",
        "fuera": "外",
        "fuerte": "強い",
        "fumar": "喫煙する",
        "fumador": "喫煙者",
        "fumadora": "喫煙者",
        "fútbol": "サッカー",
        "fútbol americano": "アメリカンフットボール",
        "futbolista": "サッカー選手",
        "futuro": "未来",
        "gafas": "メガネ",
        "gafas de sol": "サングラス",
        "gana": "勝つ",
        "ganar": "勝つ",
        "garaje": "ガレージ",
        "garganta": "喉",
        "gasolina": "ガソリン",
        "gato": "猫",
        "gata": "猫",
        "general": "一般的な",
        "genial": "素晴らしい",
        "gente": "人々",
        "girar": "回転する",
        "gobierno": "政府",
        "golf": "ゴルフ",
        "goma": "消しゴム",
        "gordo": "太った",
        "gorda": "太った",
        "gorra": "キャップ",
        "gorro": "帽子",
        "gozar": "楽しむ",
        "grabación": "録音",
        "gracias": "ありがとう",
        "gramática": "文法",
        "grande": "大きい",
        "gratis": "無料の",
        "gratuito": "無料の",
        "gratuita": "無料の",
        "grifo": "蛇口",
        "grupo": "グループ",
        "guante": "手袋",
        "guapo": "ハンサムな",
        "guapa": "美しい",
        "Guatemala": "グアテマラ",
        "guatemalteco": "グアテマラ人",
        "guatemalteca": "グアテマラ人",
        "guerra": "戦争",
        "guitarra": "ギター",
        "gustar": "好き",
        "gusto": "好み",
        "haber": "〜している",
        "habitación": "部屋",
        "hablar": "話す",
        "hacer": "する",
        "hambre": "空腹",
        "hasta": "〜まで",
        "hecho": "事実",
        "hecha": "作られた",
        "helado": "アイスクリーム",
        "helada": "霜",
        "herido": "負傷した",
        "herida": "怪我",
        "hermano": "兄弟",
        "hermana": "姉妹",
        "hermoso": "美しい",
        "hermosa": "美しい",
        "hervir": "沸騰する",
        "hexágono": "六角形",
        "hijo": "息子",
        "hija": "娘",
        "historia": "歴史",
        "hoja": "葉",
        "hockey": "ホッケー",
        "hombre": "男性",
        "hombro": "肩",
        "hora": "時間",
        "horario": "スケジュール",
        "horaria": "毎時",
        "hormiga": "蟻（あり）",
        "horno": "オーブン",
        "hospital": "病院",
        "hotel": "ホテル",
        "hoy": "今日",
        "huevo": "卵",
        "huir": "逃げる",
        "humano": "人間",
        "humana": "人間",
        "humor": "ユーモア",
        "ida": "片道",
        "idea": "アイデア",
        "idioma": "言語",
        "iglesia": "教会",
        "igual": "同じ",
        "igualmente": "同様に",
        "imaginar": "想像する",
        "impresora": "プリンター",
        "importante": "重要な",
        "importar": "重要である",
        "increíble": "信じられない",
        "individual": "個々の",
        "inferior": "下の",
        "información": "情報",
        "informático": "コンピューター関連の",
        "informática": "情報技術",
        "Inglaterra": "イングランド",
        "ingles": "英語",
        "inglesa": "英語",
        "ingresar": "参加する",
        "iniciar": "開始する",
        "inmediatamente": "すぐに",
        "insecto": "虫（むし）",
        "inteligente": "賢い",
        "intentar": "試みる",
        "interés": "興味",
        "interesante": "面白い",
        "interesar": "興味を持つ",
        "internacional": "国際的な",
        "invierno": "冬",
        "invitado": "招待客",
        "invitada": "招待客",
        "invitar": "招待する",
        "ir": "行く",
        "isla": "島",
        "Italia": "イタリア",
        "italiano": "イタリア語",
        "italiana": "イタリア語",
        "izquierdo": "左",
        "izquierda": "左",
        "Japón": "日本",
        "japones": "日本語",
        "japonesa": "日本語",
        "jardín": "庭",
        "jarrón": "花瓶",
        "jefe": "上司",
        "jefa": "上司",
        "joven": "若い",
        "joya": "宝石",
        "juego": "ゲーム",
        "jueves": "木曜日",
        "jugador": "プレイヤー",
        "jugadora": "プレイヤー",
        "jugar": "遊ぶ",
        "juguete": "おもちゃ",
        "julio": "7月",
        "junio": "6月",
        "junto": "一緒に",
        "junta": "会議",
        "kilo": "キログラム",
        "kilómetro": "キロメートル",
        "lado": "側",
        "ladrón": "泥棒",
        "ladrona": "泥棒",
        "lagarto": "トカゲ",
        "lagarta": "トカゲ",
        "lago": "湖",
        "lágrima": "涙",
        "lámpara": "ランプ",
        "lámpara de araña": "シャンデリア",
        "lanzar": "投げる",
        "lápiz": "鉛筆",
        "largo": "長い",
        "larga": "長い",
        "lástima": "残念",
        "lata": "缶",
        "Latinoamérica": "ラテンアメリカ",
        "latinoamericano": "ラテンアメリカの",
        "latinoamericana": "ラテンアメリカの",
        "lavadora": "洗濯機",
        "lavar": "洗う",
        "le": "彼に",
        "leche": "牛乳",
        "leer": "読む",
        "lejos": "遠く",
        "lengua": "言語",
        "lento": "遅い",
        "lenta": "遅い",
        "les": "彼らに",
        "levantarse": "起きる",
        "ley": "法律",
        "libre": "自由な",
        "librería": "書店",
        "libro": "本",
        "limón": "レモン",
        "limpiar": "掃除する",
        "limpio": "きれいな",
        "limpia": "きれいな",
        "línea": "線",
        "listo": "準備ができて",
        "lista": "リスト",
        "litro": "リットル",
        "llamar": "呼ぶ",
        "llave": "鍵",
        "llegar": "着く",
        "lleno": "いっぱいの",
        "llena": "いっぱいの",
        "llevar": "持っていく",
        "llorar": "泣く",
        "llover": "雨が降る",
        "lluvia": "雨",
        "lo": "それ",
        "local": "地元の",
        "lograr": "達成する",
        "lotería": "宝くじ",
        "luego": "その後",
        "lugar": "場所",
        "luna": "月",
        "lunes": "月曜日",
        "luz": "光",
        "madera": "木材",
        "madre": "母",
        "madrugar": "早起きする",
        "maduro": "熟した",
        "madura": "熟した",
        "maestro": "先生",
        "maestra": "先生",
        "mal": "悪い",
        "maleta": "スーツケース",
        "malo": "悪い",
        "mala": "悪い",
        "mamá": "ママ",
        "mandar": "送る",
        "manera": "方法",
        "mano": "手",
        "mantener": "維持する",
        "manzana": "リンゴ",
        "mañana": "明日",
        "mapa": "地図",
        "maravilloso": "素晴らしい",
        "maravillosa": "素晴らしい",
        "marido": "夫",
        "mariposa": "蝶",
        "marisco": "貝、シーフード",
        "Marruecos": "モロッコ",
        "marroquí": "モロッコ",
        "martes": "火曜日",
        "martillo": "ハンマー",
        "marzo": "3月",
        "más": "より多く",
        "mascota": "ペット",
        "matar": "殺す",
        "matrimonio": "結婚",
        "mayo": "5月",
        "mayor": "大きい",
        "mayoría": "過半数",
        "me": "私を",
        "medicamento": "薬",
        "medicina": "医学",
        "médico": "医者",
        "médica": "医者",
        "medio": "中間",
        "media": "中間",
        "mediodía": "正午",
        "mediterráneo": "地中海",
        "mediterránea": "地中海",
        "mejilla": "ほお",
        "mejor": "より良い",
        "menor": "小さい",
        "menos": "少ない",
        "mensaje": "メッセージ",
        "mentir": "嘘をつく",
        "mentira": "嘘",
        "mentiroso": "嘘つき",
        "mentirosa": "嘘つき",
        "menudo": "しばしば",
        "menuda": "何とも",
        "mercado": "市場",
        "mes": "月",
        "mesa": "テーブル",
        "meter": "入れる",
        "metro": "メートル",
        "México": "メキシコ",
        "mexicano": "メキシコ人",
        "mexicana": "メキシコ人",
        "mi": "私の",
        "micrófono": "マイク",
        "microondas": "電子レンジ",
        "miedo": "恐れ",
        "mientras": "しながら",
        "miércoles": "水曜日",
        "mil": "千",
        "millón": "百万",
        "minuto": "分",
        "mío": "私のもの",
        "mía": "私のもの",
        "mirar": "見る",
        "mismo": "同じ",
        "misma": "同じ",
        "mixto": "混合",
        "mixta": "混合",
        "mochila": "リュックサック",
        "moda": "ファッション",
        "moderno": "現代的な",
        "moderna": "現代的な",
        "modo": "モード",
        "molestar": "邪魔する",
        "momento": "瞬間",
        "montaña": "山",
        "montar": "乗る",
        "monte": "山",
        "monumento": "記念碑",
        "morir": "死ぬ",
        "mostrar": "表示する",
        "moto": "バイク",
        "mover": "動かす",
        "móvil": "携帯電話",
        "muchacho": "少年",
        "muchacha": "少女",
        "mucho": "たくさん",
        "mucha": "たくさん",
        "muela": "歯",
        "muerto": "死んだ",
        "muerta": "死んだ",
        "mujer": "女性",
        "multa": "罰金",
        "mundo": "世界",
        "museo": "博物館",
        "música": "音楽",
        "musulmán": "ムスリム",
        "musulmana": "ムスリム",
        "muy": "とても",
        "nacer": "生まれる",
        "nacional": "国民の",
        "nada": "何も",
        "nadar": "泳ぐ",
        "nadie": "誰も",
        "naranja": "オレンジ",
        "nariz": "鼻",
        "natación": "水泳",
        "natural": "自然な",
        "Navidad": "クリスマス",
        "necesario": "必要な",
        "necesaria": "必要な",
        "negar": "否定する",
        "negocio": "ビジネス",
        "negro": "黒",
        "negra": "黒",
        "nervioso": "神経質な",
        "nerviosa": "神経質な",
        "neumático": "タイヤ",
        "nevar": "雪が降る",
        "nevera": "冷蔵庫",
        "ni": "も、または",
        "niebla": "霧",
        "nieto": "孫",
        "nieta": "孫",
        "nieve": "雪",
        "ninguno": "どれも",
        "ninguna": "どれも",
        "niño": "子供",
        "niña": "女の子",
        "nivel": "レベル",
        "noche": "夜",
        "nombre": "名前",
        "normal": "通常の",
        "norte": "北",
        "norteamericano": "北米の",
        "norteamericana": "北米の",
        "nos": "私たちに",
        "nosotros": "私たち",
        "nosotras": "私たち",
        "noticia": "ニュース",
        "novela": "小説",
        "noviembre": "11月",
        "novio": "彼氏",
        "novia": "彼女",
        "nube": "雲",
        "nublado": "曇り",
        "nublada": "曇り",
        "nuestro": "私たちの",
        "nuestra": "私たちの",
        "nuevo": "新しい",
        "nueva": "新しい",
        "número": "番号",
        "nunca": "決して",
        "obra": "作品",
        "ocasión": "機会",
        "occidental": "西洋の",
        "océano": "海洋",
        "octubre": "10月",
        "ocupado": "忙しい",
        "ocupada": "忙しい",
        "ocurrir": "起こる",
        "oeste": "西",
        "oficina": "オフィス",
        "oído": "耳",
        "oír": "聞く",
        "ojo": "目",
        "oler": "匂いをかぐ",
        "olvidar": "忘れる",
        "opinión": "意見",
        "orden": "順序",
        "ordenador": "コンピュータ",
        "oreja": "耳",
        "oriental": "東洋の",
        "origen": "起源",
        "original": "オリジナル",
        "oro": "金",
        "os": "あなたたちを",
        "oscuro": "暗い",
        "oscura": "暗い",
        "oso": "熊（くま）",
        "osa": "熊（くま）",
        "otoño": "秋",
        "otro": "別の",
        "otra": "別の",
        "oveja": "羊",
        "paciencia": "忍耐",
        "paciente": "患者",
        "padre": "父",
        "paella": "パエリア",
        "pagar": "支払う",
        "país": "国",
        "pájaro": "鳥",
        "palabra": "言葉",
        "pálido": "青白い",
        "pálida": "青白い",
        "palomitas": "ポップコーン",
        "pan": "パン",
        "pantalón": "ズボン",
        "papá": "パパ",
        "papel": "紙",
        "paquete": "パッケージ",
        "para": "ために",
        "parada": "停留所",
        "paraguas": "傘",
        "parar": "止める",
        "parecer": "見える",
        "parecido": "似た",
        "parecida": "似た",
        "pared": "壁",
        "pareja": "カップル",
        "pariente": "親戚",
        "parque": "公園",
        "parte": "部分",
        "particular": "特定の",
        "partido": "試合",
        "partir": "出発する",
        "pasado": "過去",
        "pasada": "過去の",
        "pasado mañana": "明後日",
        "pasajero": "乗客",
        "pasajera": "乗客",
        "pasaporte": "パスポート",
        "pasar": "過ごす",
        "pasear": "散歩する",
        "paseo": "散歩",
        "pasillo": "廊下",
        "pastel": "ケーキ",
        "patata": "ジャガイモ",
        "paz": "平和",
        "pedir": "頼む",
        "peinarse": "髪をとかす",
        "peine": "くし",
        "película": "映画",
        "peligroso": "危険な",
        "peligrosa": "危険な",
        "pelo": "髪",
        "pelota": "ボール",
        "pena": "悲しみ",
        "península": "半島",
        "pensar": "考える",
        "pentágono": "五角形",
        "peor": "最悪の",
        "pequeño": "小さい",
        "pequeña": "小さい",
        "perder": "失う",
        "perdón": "ごめんなさい",
        "perdonar": "許す",
        "perezoso": "怠惰な",
        "perezosa": "怠惰な",
        "periódico": "新聞",
        "periodista": "ジャーナリスト",
        "período": "期間",
        "periodo": "期間",
        "permiso": "許可",
        "permitir": "許可する",
        "pero": "しかし",
        "perro": "犬（いぬ）",
        "perra": "犬（いぬ）",
        "persona": "人（ひと）",
        "Perú": "ペルー",
        "peruano": "ペルー人",
        "peruana": "ペルー人",
        "pesado": "重い",
        "pesada": "重い",
        "pesca": "釣り",
        "pescado": "魚（さかな）",
        "pescar": "釣る",
        "pez": "魚（さかな）",
        "piano": "ピアノ",
        "pianista": "ピアニスト",
        "pico": "ピーク",
        "pie": "足",
        "pierna": "脚",
        "piloto": "パイロット",
        "pintar": "絵を描く",
        "pintor": "画家",
        "pintora": "画家",
        "piscina": "プール",
        "piso": "階",
        "placer": "楽しみ",
        "plano": "平らな",
        "plana": "平らな",
        "planta": "工場",
        "plata": "銀",
        "plátano": "バナナ",
        "plato": "皿",
        "playa": "ビーチ",
        "plaza": "広場",
        "pluma": "ペン",
        "pobre": "貧しい",
        "poco": "少し",
        "poca": "少し",
        "poder": "力",
        "poema": "詩",
        "policía": "警察",
        "pollo": "鶏肉",
        "poner": "置く",
        "popular": "人気のある",
        "por": "によって",
        "porque": "なぜなら",
        "Portugal": "ポルトガル",
        "portugués": "ポルトガルの",
        "portuguesa": "ポルトガルの",
        "posible": "可能",
        "practicar": "練習",
        "precio": "価格",
        "precioso": "美しい",
        "preciosa": "美しい",
        "preferir": "好む",
        "pregunta": "質問",
        "preguntar": "尋ねる",
        "preocupar": "心配",
        "preparar": "用意する",
        "presidente": "社長",
        "presidenta": "社長",
        "prestar": "提供する",
        "primario": "第一の",
        "primaria": "第一の",
        "primavera": "春",
        "primero": "第一",
        "primera": "第一",
        "primo": "いとこ",
        "prima": "従兄弟",
        "principal": "主要な",
        "prisa": "急ぐ",
        "probable": "おそらく",
        "problema": "問題",
        "producir": "生産する",
        "profesión": "職業",
        "profesor": "教師",
        "profesora": "教師",
        "programa": "プログラム",
        "prohibido": "禁止された",
        "prohibida": "禁止された",
        "prohibir": "禁止する",
        "pronto": "すぐに",
        "pronta": "すぐに",
        "propio": "独自の",
        "propia": "独自の",
        "propósito": "目的",
        "próximo": "次の",
        "próxima": "次の",
        "público": "公の",
        "pública": "公の",
        "pueblo": "町",
        "puente": "橋",
        "puerta": "ドア",
        "puerto": "港",
        "Puerto Rico": "プエルトリコ",
        "pues": "だから",
        "puesto": "職",
        "puesta": "日没",
        "punto": "点",
        "puntual": "時間厳守の",
        "que": "その",
        "qué": "何",
        "quedar": "残る",
        "quejarse": "不満を言う",
        "quemar": "焼く",
        "querer": "欲しい",
        "quien": "誰",
        "quién": "誰",
        "quinientos": "五百",
        "quiosco": "屋台",
        "quitar": "取り除く",
        "radio": "ラジオ",
        "rápido": "速い",
        "rápida": "速い",
        "raro": "珍しい",
        "rara": "珍しい",
        "rato": "時間",
        "razón": "理由",
        "real": "実際の",
        "realidad": "現実",
        "recepcionista": "受付係",
        "recibir": "受け取る",
        "recoger": "集める",
        "recomendar": "勧める",
        "recordar": "覚える",
        "rectangular": "長方形",
        "recuerdo": "思い出",
        "regalar": "贈る",
        "regalo": "贈り物",
        "región": "地域",
        "regresar": "戻る",
        "regular": "定期的な",
        "reír": "笑う",
        "relación": "関係",
        "religión": "宗教",
        "reloj": "時計",
        "remedio": "治療法",
        "representar": "表す",
        "reservar": "予約する",
        "resfriado": "風邪",
        "resfriada": "風邪",
        "residencia": "住宅",
        "resolver": "解決する",
        "respetar": "尊重する",
        "responder": "答える",
        "restaurante": "レストラン",
        "resultado": "結果",
        "retraso": "遅延",
        "reunión": "会議",
        "reunir": "集める",
        "revista": "雑誌",
        "rey": "王",
        "reina": "女王",
        "rico": "豊かな",
        "rica": "豊かな",
        "río": "川",
        "robar": "盗む",
        "rojo": "赤",
        "roja": "赤",
        "romper": "壊す",
        "ropa": "服",
        "roto": "壊れた",
        "rota": "壊れた",
        "rubio": "金髪",
        "rubia": "金髪",
        "rugby": "ラグビー",
        "ruido": "騒音",
        "rumor": "噂",
        "rural": "田舎の",
        "Rusia": "ロシア",
        "ruso": "ロシアの",
        "rusa": "ロシアの",
        "ruta": "経路",
        "sábado": "土曜日",
        "saber": "知る",
        "sabroso": "おいしい",
        "sabrosa": "おいしい",
        "sacar": "取り出す",
        "sala": "部屋",
        "salida": "出口",
        "salir": "出る",
        "salón": "サロン",
        "salud": "健康",
        "saludar": "挨拶する",
        "sangre": "血",
        "sano": "健康な",
        "sana": "健康な",
        "sartén": "フライパン",
        "satisfecho": "満足した",
        "satisfecha": "満足した",
        "se": "彼ら",
        "seco": "乾いた",
        "seca": "乾いた",
        "secretario": "書記",
        "secretaria": "書記",
        "secundario": "二次的な",
        "secundaria": "二次的な",
        "sed": "喉の渇き",
        "seguir": "続ける",
        "segundo": "秒",
        "segunda": "秒",
        "seguro": "安全な",
        "segura": "安全な",
        "sello": "印",
        "semáforo": "信号",
        "semana": "週",
        "sencillo": "簡単な",
        "sencilla": "簡単な",
        "sentar": "座る",
        "sentido": "意味",
        "sentir": "感じる",
        "señor": "紳士",
        "señora": "女性",
        "señorita": "お嬢さん",
        "septiembre": "9月",
        "ser": "存在する",
        "serio": "真剣な",
        "seria": "真剣な",
        "servicio": "サービス",
        "servir": "提供する",
        "si": "はい",
        "sí": "はい",
        "siempre": "常に",
        "siglo": "世紀",
        "siguiente": "次の",
        "silla": "椅子",
        "silla de ruedas": "車椅子",
        "sillón": "アームチェア",
        "simpático": "親切な",
        "simpática": "親切な",
        "sin": "なし",
        "situación": "状況",
        "sobre": "上に",
        "sobrino": "甥",
        "sobrina": "姪",
        "sofbol": "ソフトボール",
        "sofá": "ソファ",
        "sol": "太陽",
        "soler": "する傾向がある",
        "sólo": "だけ",
        "solo": "だけ",
        "sola": "だけ",
        "soltero": "独身の",
        "soltera": "独身の",
        "solucionar": "解決する",
        "sombra": "影",
        "sombrero": "帽子",
        "sonreír": "笑顔である",
        "sopa": "スープ",
        "sorpresa": "驚き",
        "su": "彼の",
        "suave": "滑らかな",
        "subir": "上がる",
        "sucio": "汚れた",
        "sucia": "汚れた",
        "suelo": "床",
        "suelto": "緩い",
        "suelta": "解放された",
        "suerte": "幸運",
        "sufrir": "苦しむ",
        "superior": "上位の",
        "supermercado": "スーパーマーケット",
        "supuesto": "仮定された",
        "sur": "南",
        "surf": "サーフィン",
        "suyo": "彼の",
        "suya": "彼女の",
        "tal": "そのような",
        "talla": "サイズ",
        "también": "もまた",
        "tampoco": "また",
        "tan": "とても",
        "tanto": "たくさん",
        "tanta": "そんなに",
        "taquilla": "切符売り場",
        "tardar": "遅れる",
        "tarde": "遅く",
        "tarea": "仕事",
        "tarifa": "料金",
        "tarjeta": "カード",
        "tarta": "タルト",
        "taxi": "タクシー",
        "taza": "カップ",
        "te": "お茶",
        "té": "お茶",
        "teatro": "劇場",
        "técnico": "技術者",
        "técnica": "技術",
        "teclado": "キーボード",
        "teléfono": "電話",
        "televisión": "テレビ",
        "tema": "テーマ",
        "temperatura": "温度",
        "temprano": "早い",
        "tenedor": "フォーク", 
        "tener": "持っている",
        "tenis": "テニス",
        "tenis de mesa": "卓球",
        "tercero": "第三の",
        "tercera": "第三の",
        "terminal": "ターミナル",
        "terminar": "終える",
        "terremoto": "地震",
        "terrible": "ひどい",
        "terror": "恐怖",
        "tiempo": "時間",
        "tienda": "店",
        "tierno": "柔らかい",
        "tierna": "柔らかい",
        "tierra": "地球、大地",
        "tifón": "台風",
        "tijera": "はさみ",
        "timbre": "ベル",
        "tímido": "内気な",
        "tímida": "内気な",
        "tinto": "赤ワイン",
        "tinta": "インク",
        "tío": "おじさん",
        "tía": "おばさん",
        "típico": "典型的な",
        "típica": "典型的な",
        "tipo": "種類",
        "tirar": "投げる",
        "toalla": "タオル",
        "tocar": "触れる",
        "todavía": "まだ",
        "todo": "全て",
        "toda": "全て",
        "tomar": "取る",
        "tornado": "トルネード",
        "torcer": "ねじる",
        "toro": "牛",
        "torre": "塔",
        "tortilla": "トルティーヤ",
        "tos": "咳",
        "tortuga": "亀（かめ）",
        "trabajador": "労働者",
        "trabajadora": "労働者",
        "trabajar": "働く",
        "trabajo": "仕事",
        "traducir": "翻訳する",
        "traer": "持ってくる",
        "tráfico": "交通",
        "traje": "スーツ",
        "tranquilo": "静かな",
        "tranquila": "静かな",
        "tren": "電車",
        "tren bala": "新幹線",
        "triángulo": "三角形",
        "trueno": "雷",
        "tú": "あなた",
        "tu": "あなたの",
        "turismo": "観光",
        "turista": "観光客",
        "tuyo": "あなたの",
        "tuya": "あなたの",
        "último": "最後の",
        "última": "最後の",
        "universidad": "大学",
        "usar": "使用する",
        "usted": "あなた",
        "útil": "役に立つ",
        "uva": "ブドウ",
        "vaca": "牛",
        "vacación": "休暇",
        "vacío": "空の",
        "vacía": "空の",
        "valer": "価値がある",
        "valle": "谷",
        "vaquero": "カウボーイ",
        "vaquera": "カウガール",
        "vario": "さまざまな",
        "varia": "さまざまな",
        "vaso": "グラス",
        "vecino": "隣人",
        "vecina": "隣人",
        "vender": "売る",
        "venir": "来る",
        "venta": "販売",
        "ventana": "窓",
        "ventanilla": "窓口",
        "ventilador": "扇風機",
        "ver": "見る",
        "verano": "夏",
        "verdad": "真実",
        "verdadero": "真の",
        "verdadera": "真の",
        "verde": "緑",
        "verdura": "野菜",
        "vestido": "ドレス",
        "vestir": "着る",
        "vez": "回",
        "viajar": "旅行する",
        "viaje": "旅",
        "viajero": "旅行者",
        "viajera": "旅行者",
        "vida": "人生",
        "videojuego": "ビデオゲーム",
        "viejo": "古い",
        "vieja": "古い",
        "viento": "風",
        "viernes": "金曜日",
        "vino": "ワイン",
        "visitar": "訪問する",
        "visto": "見る",
        "vista": "眺め",
        "vivir": "生きる",
        "volar": "飛ぶ",
        "voleibol": "バレーボール",
        "volver": "戻る",
        "vosotros": "あなたたち",
        "vosotras": "あなたたち",
        "voz": "声",
        "vuelo": "飛行",
        "vuelta": "戻り",
        "vuestro": "あなたたちの",
        "vuestra": "あなたたちの",
        "y": "そして",
        "ya": "もう",
        "yate": "ヨット",
        "yo": "私",
        "yoga": "ヨガ",
        "zapatilla": "スリッパ",
        "zapato": "靴",
        "zona": "地域",
        "zoo": "動物園",
        "zoológico": "動物園",
        "zumo": "ジュース"
}